mp_dev/__init__.py
mp_dev/cli.py
mp_dev/project_generator.py
mp_dev/commands/__init__.py
mp_dev/commands/help_command.py
mp_dev/commands/init_command.py
mp_dev/templates/__init__.py
mp_dev/templates/config_template.py
mp_dev/templates/connection_template.py
mp_dev/templates/data_base_session_middleware_template.py
mp_dev/templates/docker_compose_template.py
mp_dev/templates/dockerfile_template.py
mp_dev/templates/gitignore_template.py
mp_dev/templates/is_authenticated_middleware_template.py
mp_dev/templates/main_template.py
mp_dev/templates/migration_template.py
mp_dev/templates/token_schema_template.py
mp_dev/templates/user_controller_template.py
mp_dev/templates/user_model_template.py
mp_dev-1.1.1.dist-info/METADATA
mp_dev-1.1.1.dist-info/WHEEL
mp_dev-1.1.1.dist-info/entry_points.txt
mp_dev-1.1.1.dist-info/top_level.txt
mp_dev-1.1.1.dist-info/RECORD
