Metadata-Version: 2.1
Name: mp_dev
Version: 1.1.1
Summary: A FastAPI plugin for generating project structures
Home-page: https://github.com/Marshall-Pierre
Author: MarshallPierre
Author-email: nguemazengmp@gmail.com
Classifier: Programming Language :: Python :: 3
Classifier: License :: OSI Approved :: MIT License
Classifier: Operating System :: OS Independent
Requires-Python: >=3.6
Requires-Dist: fastapi
Requires-Dist: uvicorn[standard]
Requires-Dist: python-jose[cryptography]
Requires-Dist: passlib[bcrypt]
Requires-Dist: sqlalchemy
